[
  {
    "pathway_id": "LP_OPERATIONS_FOUNDATION",
    "domain": "Operations",
    "level": "Foundation",
    "mapped_skills": {
      "SK_ACCOUNTABILITY": "primary",
      "SK_COLLABORATION": "primary",
      "SK_COMMUNICATION_CLARITY": "secondary",
      "SK_DECISION_MAKING": "secondary"
    },
    "intended_outcomes": [
      "Understand operational workflows",
      "Coordinate tasks and stakeholders",
      "Apply structured decision-making"
    ],
    "modules": [
      "Introduction to Business Operations",
      "Workplace Coordination & Communication",
      "Decision-Making in Operational Contexts"
    ],
    "certification": {
      "type": "Certificate",
      "issued_by": "CIF Learning Wing",
      "validated_by": ["industry_experts", "academic_review"]
    },
    "delivery_modes": ["online", "blended"],
    "eligibility": {
      "min_cif_score": 60,
      "recommended_bands": ["Developing", "Established"]
    }
  },
  {
    "pathway_id": "LP_HR_FOUNDATION",
    "domain": "Human Resources",
    "level": "Foundation",
    "mapped_skills": {
      "SK_COMMUNICATION_CLARITY": "primary",
      "SK_COLLABORATION": "primary",
      "SK_EMOTIONAL_REGULATION": "secondary",
      "SK_DECISION_MAKING": "secondary"
    },
    "intended_outcomes": [
      "Understand HR functions and processes",
      "Develop people-facing communication",
      "Apply ethical and emotional awareness"
    ],
    "modules": [
      "Core HR Functions",
      "Workplace Communication & Ethics",
      "People-Centric Decision Making"
    ],
    "certification": {
      "type": "Certificate",
      "issued_by": "CIF Learning Wing",
      "validated_by": ["industry_experts", "academic_review"]
    },
    "delivery_modes": ["online"],
    "eligibility": {
      "min_cif_score": 58,
      "recommended_bands": ["Developing"]
    }
  }
]
